chaostools/__init__.py
chaostools-0.0.8.dist-info/LICENSE
chaostools-0.0.8.dist-info/METADATA
chaostools-0.0.8.dist-info/WHEEL
chaostools-0.0.8.dist-info/top_level.txt
chaostools-0.0.8.dist-info/RECORD
