Metadata-Version: 2.1
Name: chaostools
Version: 0.0.8
Summary: They're really some great tools!
Home-page: https://gitee.com/wang-chenfan/chaostools
Author: WCF
Author-email: admin@wcfstudio.cn
License: MIT
Platform: UNKNOWN
Classifier: Development Status :: 3 - Alpha
Classifier: Intended Audience :: Developers
Classifier: License :: OSI Approved :: MIT License
Classifier: Programming Language :: Python
Classifier: Programming Language :: Python :: 3
Classifier: Programming Language :: Python :: 3.6
Classifier: Programming Language :: Python :: 3.7
Classifier: Programming Language :: Python :: 3.8
Classifier: Programming Language :: Python :: 3.9
Requires-Dist: bs4
Requires-Dist: beautifulsoup4
Requires-Dist: requests
Requires-Dist: lxml
